[
   {
      "id": 1,
      "image": "@img/home/products/03.webp",
      "title": "AROMISTICO Coffee 1 kg",
      "price": 6.99,
      "country": "Brazil"
   },
   {
      "id": 2,
      "image": "@img/home/products/03.webp",
      "title": "SEGAFREDO Intermezzo 1 kg",
      "price": 7.49,
      "country": "Brazil"
   },
   {
      "id": 3,
      "image": "@img/home/products/03.webp",
      "title": "KENYA AA Premium 500g",
      "price": 5.99,
      "country": "Kenya"
   },
   {
      "id": 4,
      "image": "@img/home/products/03.webp",
      "title": "KENYA Safari Roast 250g",
      "price": 4.79,
      "country": "Kenya"
   },
   {
      "id": 5,
      "image": "@img/home/products/03.webp",
      "title": "COLOMBIA Supremo 1 kg",
      "price": 8.25,
      "country": "Columbia"
   },
   {
      "id": 6,
      "image": "@img/home/products/03.webp",
      "title": "COLOMBIA Sierra Nevada 500g",
      "price": 5.49,
      "country": "Columbia"
   },
   {
      "id": 7,
      "image": "@img/home/products/03.webp",
      "title": "AROMISTICO Coffee 1 kg",
      "price": 6.99,
      "country": "Brazil"
   },
   {
      "id": 8,
      "image": "@img/home/products/03.webp",
      "title": "SEGAFREDO Intermezzo 1 kg",
      "price": 7.49,
      "country": "Brazil"
   },
   {
      "id": 9,
      "image": "@img/home/products/03.webp",
      "title": "KENYA AA Premium 500g",
      "price": 5.99,
      "country": "Kenya"
   },
   {
      "id": 10,
      "image": "@img/home/products/03.webp",
      "title": "KENYA Safari Roast 250g",
      "price": 4.79,
      "country": "Kenya"
   },
   {
      "id": 11,
      "image": "@img/home/products/03.webp",
      "title": "COLOMBIA Supremo 1 kg",
      "price": 8.25,
      "country": "Columbia"
   },
   {
      "id": 12,
      "image": "@img/home/products/03.webp",
      "title": "COLOMBIA Sierra Nevada 500g",
      "price": 5.49,
      "country": "Columbia"
   }
]
